{
    "modular": false,
    "data": [
        {
            "url": "https://fcc.report//FCC-ID/KA2IR615I1/1573317.pdf",
            "name": "1573317.pdf",
            "type": "Cover Letter(s)",
            "description": "Cover Letter Contact Authorization",
            "date": "2011-11-03",
            "sha256": "17a3ca6f0421cfdffed420d3b13ef05322937d28f696ac34775f53134bc95897"
        },
        {
            "url": "https://fcc.report//FCC-ID/KA2IR615I1/1573316.pdf",
            "name": "1573316.pdf",
            "type": "Cover Letter(s)",
            "description": "Cover Letter Agent Authorization",
            "date": "2011-11-03",
            "sha256": "abe2efb704ede35d2ffd302d9af365bf447d1f161eac104703a8299a61e7055e"
        },
        {
            "url": "https://fcc.report//FCC-ID/KA2IR615I1/1573315.pdf",
            "name": "1573315.pdf",
            "type": "Cover Letter(s)",
            "description": "Confidentiality Request",
            "date": "2011-11-03",
            "sha256": "1c506710ef27742fc63cfcebcd63c7aa358e065ebb2809e8e749cb54ae1fcf8b"
        },
        {
            "url": "https://fcc.report//FCC-ID/KA2IR615I1/1573314.pdf",
            "name": "1573314.pdf",
            "type": "Attestation Statements",
            "description": "Attestation Statement Channel Declaration",
            "date": "2011-11-03",
            "sha256": "9212d67f9e32f9a5f584590ce3dc531617b628851d1577c84899d6db5ede2bb2"
        },
        {
            "url": "https://fcc.report//FCC-ID/KA2IR615I1/1573313.pdf",
            "name": "1573313.pdf",
            "type": "RF Exposure Info",
            "description": "RF Exposure Info",
            "date": "2011-11-03",
            "sha256": "38e01d7a5cb5fb2659beb753c87f054057649bbf55c9662c90b90b3a4a7830ff"
        },
        {
            "url": "https://fcc.report//FCC-ID/KA2IR615I1/1573312.pdf",
            "name": "1573312.pdf",
            "type": "Users Manual",
            "description": "User Manual",
            "date": "2011-11-03",
            "sha256": "b21dc18aec9158b91fa80ba97d9c9b7bf4af69fbbf0e27ccb9a719c8161f9efc"
        },
        {
            "url": "https://fcc.report//FCC-ID/KA2IR615I1/1573311.pdf",
            "name": "1573311.pdf",
            "type": "Test Setup Photos",
            "description": "Test Setup Photos",
            "date": "2011-11-03",
            "sha256": "4f32beadddbd18d6a50a355143d5772742f42af50b287a86b457666334ab6847"
        },
        {
            "url": "https://fcc.report//FCC-ID/KA2IR615I1/1573310.pdf",
            "name": "1573310.pdf",
            "type": "Test Report",
            "description": "Test Report",
            "date": "2011-11-03",
            "sha256": "77596924c55f44d4b27952ea7dcc0a5dc3bb3333fbc9f40ea2aaa7cd6c7be181"
        },
        {
            "url": "https://fcc.report//FCC-ID/KA2IR615I1/1573308.pdf",
            "name": "1573308.pdf",
            "type": "Operational Description",
            "description": "Operational Description",
            "date": "2011-11-03",
            "sha256": "8e79f7f81ec8b67e418969ac62263a0d0fb7462318bd977009500e465511cb93"
        },
        {
            "url": "https://fcc.report//FCC-ID/KA2IR615I1/1573307.pdf",
            "name": "1573307.pdf",
            "type": "Internal Photos",
            "description": "Internal Photos",
            "date": "2011-11-03",
            "sha256": "a3a649e8d1b058ec0219c6f5b67b3f3b6a095bd3f4ab3d2ea5c629e9c8c33854"
        },
        {
            "url": "https://fcc.report//FCC-ID/KA2IR615I1/1573306.pdf",
            "name": "1573306.pdf",
            "type": "ID Label/Location Info",
            "description": "Label Location",
            "date": "2011-11-03",
            "sha256": "177de4ce2bc2e25f5b632306a45eedee3428f1f22bc0df30718cdaad8f3afbf5"
        },
        {
            "url": "https://fcc.report//FCC-ID/KA2IR615I1/1573305.pdf",
            "name": "1573305.pdf",
            "type": "ID Label/Location Info",
            "description": "Label",
            "date": "2011-11-03",
            "sha256": "2d65e0359b833574a28b30a86fc60b0be2aa124702e47e841c39a535119ae2f4"
        },
        {
            "url": "https://fcc.report//FCC-ID/KA2IR615I1/1573304.pdf",
            "name": "1573304.pdf",
            "type": "External Photos",
            "description": "External Photos",
            "date": "2011-11-03",
            "sha256": "0b298b976320176be40dc58c6949b598cb2c156abcb698bea0c5035a7a3417ec"
        }
    ]
}