{
    "type": "overlay",
    "name": "fcc_extracted_text",
    "source": "fcc",
    "data": [
        {
            "fcc_id": "PY315100302",
            "pdf": "2629450.pdf",
            "type": "Users Manual",
            "description": "Users Manual.pdf",
            "hints": [
                {
                    "page": 11,
                    "results": [
                        {
                            "type": "reference",
                            "value": "default password"
                        }
                    ]
                },
                {
                    "page": 13,
                    "results": [
                        {
                            "type": "reference",
                            "value": "default password"
                        }
                    ]
                },
                {
                    "page": 14,
                    "results": [
                        {
                            "type": "reference",
                            "value": "default password"
                        },
                        {
                            "type": "reference",
                            "value": "default user"
                        }
                    ]
                }
            ]
        }
    ]
}