{
    "modular": false,
    "data": [
        {
            "url": "https://fcc.report//FCC-ID/NKR-DTVDCCK/1411665.pdf",
            "name": "1411665.pdf",
            "type": "Users Manual",
            "description": "User Manual",
            "date": "2011-01-31",
            "sha256": "0c222c439c292cf117a13238133a3f0e800c0a0fbd7c7b9d49cd949676f40b2a"
        },
        {
            "url": "https://fcc.report//FCC-ID/NKR-DTVDCCK/1411664.pdf",
            "name": "1411664.pdf",
            "type": "Cover Letter(s)",
            "description": "Uniform spreading Declaration letter",
            "date": "2011-01-31",
            "sha256": "da8b9513625b74d142df272c9a947e3c06872e43eeb78adec2c2e2ccf86d8a01"
        },
        {
            "url": "https://fcc.report//FCC-ID/NKR-DTVDCCK/1411660.pdf",
            "name": "1411660.pdf",
            "type": "RF Exposure Info",
            "description": "MPE",
            "date": "2011-01-31",
            "sha256": "0150af31fe86060885c8afac16a4074b72553e82f3311eaa124c624ac5476b60"
        },
        {
            "url": "https://fcc.report//FCC-ID/NKR-DTVDCCK/1411659.pdf",
            "name": "1411659.pdf",
            "type": "ID Label/Location Info",
            "description": "Label Location",
            "date": "2011-01-31",
            "sha256": "385db21f34a0ecfcf305f69e2c606b27fa602a1fe5250b7e63cea95e5fe0b378"
        },
        {
            "url": "https://fcc.report//FCC-ID/NKR-DTVDCCK/1411656.pdf",
            "name": "1411656.pdf",
            "type": "Cover Letter(s)",
            "description": "DOC letter",
            "date": "2011-01-31",
            "sha256": "34992d08eeac756fe22dcd97a1e45dc7b341e9ca0f9d737eb936de3fb6e7c55b"
        },
        {
            "url": "https://fcc.report//FCC-ID/NKR-DTVDCCK/1411655.pdf",
            "name": "1411655.pdf",
            "type": "Test Report",
            "description": "DFS Report",
            "date": "2011-01-31",
            "sha256": "7cdbc9c46572a621b43f8af59302b4b5a54dca61c438ca81c2451526eb7d5433"
        },
        {
            "url": "https://fcc.report//FCC-ID/NKR-DTVDCCK/1411654.pdf",
            "name": "1411654.pdf",
            "type": "Cover Letter(s)",
            "description": "Confidential Request",
            "date": "2011-01-31",
            "sha256": "1def0528f9007a882411d9fdd129fb35e966efdb1979a67445f301d7838a0f0b"
        },
        {
            "url": "https://fcc.report//FCC-ID/NKR-DTVDCCK/1411653.pdf",
            "name": "1411653.pdf",
            "type": "Cover Letter(s)",
            "description": "Ad hoc mode",
            "date": "2011-01-31",
            "sha256": "b22bcf9c050d9f62176cea5cbf395c83a73412e1a1238bd15a0a8be17a85e688"
        },
        {
            "url": "https://fcc.report//FCC-ID/NKR-DTVDCCK/1411618.pdf",
            "name": "1411618.pdf",
            "type": "Cover Letter(s)",
            "description": "confidential request",
            "date": "2011-01-31",
            "sha256": "1def0528f9007a882411d9fdd129fb35e966efdb1979a67445f301d7838a0f0b"
        },
        {
            "url": "https://fcc.report//FCC-ID/NKR-DTVDCCK/1411617.pdf",
            "name": "1411617.pdf",
            "type": "Cover Letter(s)",
            "description": "Ad hoc mode letter",
            "date": "2011-01-31",
            "sha256": "b22bcf9c050d9f62176cea5cbf395c83a73412e1a1238bd15a0a8be17a85e688"
        },
        {
            "url": "https://fcc.report//FCC-ID/NKR-DTVDCCK/1438516.pdf",
            "name": "1438516.pdf",
            "type": "Cover Letter(s)",
            "description": "Class II letter photo",
            "date": "2011-03-28",
            "sha256": "54c83ec53a75f25894a6b7475f8a2e2f9af04951cf20ec97eeb5a3d9cd661d66"
        },
        {
            "url": "https://fcc.report//FCC-ID/NKR-DTVDCCK/1438515.pdf",
            "name": "1438515.pdf",
            "type": "Test Report",
            "description": "Test Report",
            "date": "2011-03-28",
            "sha256": "a9db5e9ba20d5efa356a2b561d29bed6d1273d1d6c6a470b78bfaee6bbf753c5"
        },
        {
            "url": "https://fcc.report//FCC-ID/NKR-DTVDCCK/1438514.pdf",
            "name": "1438514.pdf",
            "type": "Test Setup Photos",
            "description": "Test Setup Photos",
            "date": "2011-03-28",
            "sha256": "b473d4c55440c1e4813b23066905ffeccc0578ad210e61c134934b8151792acc"
        },
        {
            "url": "https://fcc.report//FCC-ID/NKR-DTVDCCK/1438513.pdf",
            "name": "1438513.pdf",
            "type": "Cover Letter(s)",
            "description": "PoA",
            "date": "2011-03-28",
            "sha256": "91c82061625d346900d4660ffe790056c9400e71ca8bf8c8b01749421770ff3a"
        },
        {
            "url": "https://fcc.report//FCC-ID/NKR-DTVDCCK/1438512.pdf",
            "name": "1438512.pdf",
            "type": "Internal Photos",
            "description": "Internal Photos",
            "date": "2011-03-28",
            "sha256": "b35093592d79e95a55359d1fcef028636af02adc4a7375f5110396188908979a"
        },
        {
            "url": "https://fcc.report//FCC-ID/NKR-DTVDCCK/1438511.pdf",
            "name": "1438511.pdf",
            "type": "External Photos",
            "description": "External Photos",
            "date": "2011-03-28",
            "sha256": "5027e89096ec9bf6bb12fc98b608749b0d1bf69ee3133e859bb2887558344054"
        },
        {
            "url": "https://fcc.report//FCC-ID/NKR-DTVDCCK/1438510.pdf",
            "name": "1438510.pdf",
            "type": "Cover Letter(s)",
            "description": "Confidential letter",
            "date": "2011-03-28",
            "sha256": "4e1bf93583eea5ba90e7cfdd042ec03240cc9a0a2952eea639124cf4a04c7bad"
        },
        {
            "url": "https://fcc.report//FCC-ID/NKR-DTVDCCK/1438509.pdf",
            "name": "1438509.pdf",
            "type": "Cover Letter(s)",
            "description": "Class II Letter",
            "date": "2011-03-28",
            "sha256": "5f453628ff0bab53310e9d8214786a28dfb7adb6cb19ce733def65c4dd61aa4d"
        },
        {
            "url": "https://fcc.report//FCC-ID/NKR-DTVDCCK/1438496.pdf",
            "name": "1438496.pdf",
            "type": "Cover Letter(s)",
            "description": "Class II Letter Photo",
            "date": "2011-03-28",
            "sha256": "54c83ec53a75f25894a6b7475f8a2e2f9af04951cf20ec97eeb5a3d9cd661d66"
        },
        {
            "url": "https://fcc.report//FCC-ID/NKR-DTVDCCK/1438491.pdf",
            "name": "1438491.pdf",
            "type": "External Photos",
            "description": "External photos",
            "date": "2011-03-28",
            "sha256": "5027e89096ec9bf6bb12fc98b608749b0d1bf69ee3133e859bb2887558344054"
        },
        {
            "url": "https://fcc.report//FCC-ID/NKR-DTVDCCK/1438490.pdf",
            "name": "1438490.pdf",
            "type": "Cover Letter(s)",
            "description": "Confidential request",
            "date": "2011-03-28",
            "sha256": "4e1bf93583eea5ba90e7cfdd042ec03240cc9a0a2952eea639124cf4a04c7bad"
        }
    ]
}