{
    "type": "overlay",
    "name": "oui",
    "source": "wireshark",
    "license": "GPL-2.0",
    "url": "https://www.wireshark.org/download/automated/data/manuf",
    "data": {
        "ethernet_oui": [
            {
                "name": "ARRIS Group, Inc.",
                "name_short": "ARRISGroup",
                "oui": "00:21:43"
            },
            {
                "name": "Motorola - BSG",
                "name_short": "MotorolaBSG",
                "oui": "00:24:37"
            }
        ],
        "wireless_oui": [
            {
                "name": "ARRIS Group, Inc.",
                "name_short": "ARRISGroup",
                "oui": "00:21:43"
            },
            {
                "name": "Motorola - BSG",
                "name_short": "MotorolaBSG",
                "oui": "00:24:37"
            }
        ]
    }
}