<page>
    <title>Belkin F7D3301</title>
    <ns>0</ns>
    <id>5494</id>
    <revision>
      <id>376099</id>
      <parentid>364835</parentid>
      <timestamp>2024-08-15T12:49:11Z</timestamp>
      <contributor>
        <username>ShadowBot</username>
        <id>3357272</id>
      </contributor>
      <minor/>
      <comment>/* top */clean up</comment>
      <origin>376099</origin>
      <model>wikitext</model>
      <format>text/x-wiki</format>
      <text bytes="8694" sha1="aefyfiuo146hei070wpzk8hurhobi9g" xml:space="preserve">{{Infobox Embedded System
|image1             = Belkin F7D3301 01.jpg
|image1_size        = 150px
|caption            = Share Max Wireless Router
|caption2           = &lt;!-- 2nd tagleine --&gt;
|pp                 = &lt;!-- product page url only --&gt;
|sp                 = http://www.belkin.com/us/support-product?rnId=5416
|dl                 = &lt;!-- Download page url only --&gt;
|fandom             = Belkin_F7D3301_v1
|wikidevi           = Belkin_F7D3301
|wikipedia          = &lt;!-- [[wikipedia:Main Page|Wikipedia]] Leave blank for none --&gt;
|ddwrtsupport       = Supported
|openwrtsupport     = Supported (Unofficially)
|tomatosupport      = Supported
|gargoylesupport    = &lt;!-- Incompatible, Not Supported, Partial Support, Supported, WIP, Unofficially, --&gt;

|brand              = Belkin
|model              = F7D3301
|submodelappend     = &lt;!-- yes, for space --&gt;
|submodel           = &lt;!-- SubModel number, Leave blank for unknown --&gt;
|revision           = v1
|subrevision        = &lt;!-- Model Subrevision, Leave blank for none or unknown --&gt;
|model_part_num     = 
|page_start_date    = 09/13/2010
|page_start_origon  = https://infodepot.fandom.com/wiki/Belkin_F7D3301_v1
|wlclass            = N300
|series             = &lt;!-- Device series --&gt;
|type               = wireless router
|sernum             = &lt;!-- First 4 or so for easy version identification --&gt;
|fcc_id             = K7SF7D3301V1
|icid               = 3623A-F7D3301V1
|us_id              = &lt;!-- US ID --&gt;
|boardid            = WG7117F22
|ecc_id             = &lt;!-- eec-id --&gt;

|cpu1chip1          = Broadcom;BCM4718A1;
|cpu1_cores         = 1
|cpu1_type          = MIPS 74Kc
|cpu1_type_rev      = &lt;!-- CPU1 type Revision, Leave blank for unknown --&gt;
|cpu1spd            = 480 &lt;!-- 480/ 533 MHz  --&gt;
|is_doc             = 
|bus                = &lt;!-- 8-bit, 16-bit, 32-bit, 64-bit, Leave blank for none --&gt;

|flash1type         = Parallel
|fla1_num           = &lt;!-- 1,2,3,4 --&gt;
|fla1chip           = Eon;EN29LV640B;CFEON (EON) EN29LV640B;
|flash1size         = 8
|flash1maxsize      = &lt;!-- Maximum size firmware can be in bytes --&gt;

|ram1type           = &lt;!-- DDR,DDR2,DDR3,DDR4 --&gt;
|ram1type1          = &lt;!-- SO-DIMM,SDRAM --&gt;
|ram1spd            = &lt;!-- RAM speed --&gt;
|ram1size           = 64
|ram1chip           = EtronTech;EM68B16CWPA-25H;EtronTech EM68B16CWPA-25H N208160AFL03811ZQ (32M x 16 bit DDRII Synchronous DRAM (SDRAM));
|ram1_num           = &lt;!-- Number of Ram chips --&gt;
|nvramsize          = &lt;!-- 32, 60, 64, etc... in kb, Leave blank for unknown --&gt;

|eth_cpu            = true
|sw1chip            = Broadcom;BCM53115;BCM53115SKFBG;
|wan_ports          = 1
|wan_speed          = 1GbE
|lan_ports          = 4
|lan_speed          = 1GbE
|ethstandard        = &lt;!-- auto --&gt;
|portbasedvlan      = &lt;!-- Support for port based vlan tagging, Leave blank for unknown --&gt;
|802.1qvlan         = &lt;!-- Support for 802.1q vlan tagging, Leave blank for unknown --&gt;
|auto_mdix          = &lt;!-- mdix support --&gt;
|sup_jumbo          = &lt;!-- Jumbo frames support --&gt;
|ethoui             = &lt;!-- Leave blank for unknown --&gt;
|oui                = &lt;!-- Leave blank for unknown --&gt;

|bootwait           = &lt;!-- On or Off, Leave blank for unknown --&gt;
|stockbootloader    = CFE;;;
|stockos            = &lt;!-- Name;Version;Distro --&gt;

|exp_if_types       = USB 2.0
|exp_usb_num        = 2
|usb_hub            = &lt;!-- USB hub compatibility --&gt;

|pwr_volt_type      = VDC
|pwr_vdc            = 12
|pwr_amp_dc         = 2
|pwr_conn           = barrel
|pwr_barrel_outer   = &lt;!-- Outer barrel size in mm --&gt;
|pwr_barrel_inner   = &lt;!-- Inner barrel size in mm --&gt;
|pwr_barrel_len     = &lt;!-- Length of barrel --&gt;
|pwr_pol            = &lt;!-- Connector polarity --&gt;

|serial             = &lt;!-- Full Serial info --&gt;
|jtag               = &lt;!-- Full JTAG info --&gt;

|specialfeat        = &lt;!-- Features that don't fit any place else, Leave blank for none --&gt;
|flags              = &lt;!-- flags, Leave blank for none --&gt;
|addchip            = &lt;!-- Additional Chips --&gt;
|802dot11_protocols = bgn

|defaulip           = &lt;!-- ???.???.???.???, default IP Address --&gt;
|defaultlogin       = &lt;!-- default Login Name, Leave blank for unknown --&gt;
|defaultpass        = &lt;!-- default Password, Leave blank for unknown --&gt;
|defaultssid        = &lt;!-- default Wireless ID, Leave blank for unknown --&gt;
|defaultssid_regex  = 
|default_ch         = &lt;!-- Defaults channel(s) Radio(s) are set to --&gt;
|manuf              = Arcadyan
|manuf_model        = WG7117F22
|manuf_rev          = &lt;!-- Manufacturer Revision --&gt;
|is_manuf           = No
|tpfirmware         = DD-WRT, FreshTomato, OpenWrt (Unofficially), TomatoUSB (Toastman)

|availability       = discontinued
|eoldate            = &lt;!-- End of Life date --&gt;
|fccapprovdate      = 06/17/2010
|estreldate         = &lt;!-- Estimated release date --&gt;
|estprice           = &lt;!-- Estimated retail price in US dollars --&gt;
|upc                = 722868807378
|ean                = &lt;!-- EAN number --&gt;
|dx_sku             = &lt;!-- DealExtreme sku --&gt;
|newegg             = N82E16833314058
|asin               = B004B1Z6EE
|asin_country       = CA
|asin2              = B004PMHF84
|asin_country2      = US
|countrymanuf       = &lt;!-- Country device was manufactured in --&gt;

|buttons            = &lt;!-- buttons available --&gt;
|led                = &lt;!-- Led colors and descriptions --&gt;
|dimensions         = &lt;!-- Size of device {{convert |length|x|widthordepth|x|height|in|mm}} --&gt;
|weight             = &lt;!-- Weight of device {{convert|weight|oz|g}} --&gt;

|wi1_if_name        = 
|rad1chip1cpu       = true
|rad1oui            = &lt;!-- Only if different from above OUI --&gt; 
|rad1_ant_conn      = &lt;!-- Leave blank for unknown --&gt;
|rad1txchains       = 2
|rad1rxchains       = 2
|rad1sstreams       = 2
|rad1stand          = IEEE 802.11b/g/n
|rad1n              = 300
|rad1g              = 54
|rad1b              = 11
|rad1freq           = 2.4
|rad1correv         = &lt;!-- core revision, Leave blank for none or unknown --&gt;
|rad1cap            = &lt;!-- radio capabilities, Leave blank for none or unknown --&gt;

}}{{TIDTOC|embedded}}
==Overview==
The default SSID may follow the pattern of '''Belkin.XXXX'''.

==Links of Interest==
*[http://www.dd-wrt.com/phpBB2/viewtopic.php?t=70454 New Belkin Routers (04/2010)] On the '''DD-WRT''' Forum
*[http://tomatousb.org/forum/t-371974/support-for-belkin-f7d7301-f7d3301 On the TomatoUSB forums]
:This device is reported to be working with recent Toastman builds.

aka '''F7D7301'''
:[http://manojpi.blogspot.com/2012/05/openwrt-on-belkin-share-max-n300.html OpenWrt on a Belkin Share Max N300 (F7D3301 or F7D7301)]

==Flashing==
{{Flashnotice}}
===Flashing dd-wrt===
{{DDWRTNotice|belkin}}

Supported by dd-wrt as of = [http://svn.dd-wrt.com:8000/dd-wrt/changeset/15156 v24 k2.6 15156]

Please insert instructions here

===Flashing OpenWrt===
aka '''F7D7301'''
{{OpenWrt
|techdata                  = 
|wikipage                  = 
|forumpage                 = 
|forumpage2                = 
|forumpage3                = 
|github                    = 
|target                    = 
|subtarget                 = 
|arch                      = 
|support_started_version   = ?
|current_supported_version = ?
|unsupportedfuncntions     = 
|comment                   = [http://manojpi.blogspot.com/2012/05/openwrt-on-belkin-share-max-n300.html OpenWrt on a Belkin Share Max N300 (F7D3301 or F7D7301)]
}}
Please insert instructions here

===Flashing Tomato===
Please insert instructions here

==USB Info==
{{USB dd-wrt}}

==Pictures==
&lt;center&gt;'''Retail Images'''
&lt;gallery&gt;
File:Belkin F7D3301 01.jpg|
File:Belkin F7D3301 02.jpg|
File:Belkin F7D3301 03.jpg|
File:Belkin F7D3301 04.jpg|
&lt;/gallery&gt;&lt;/center&gt;[[Has images::retail| ]][[Has images::external| ]]
&lt;center&gt;'''FCCID {{fccid|K7SF7D3301V1}}'''
&lt;gallery mode=&quot;slideshow&quot;&gt;
File:K7SF7D3301V1 01.png|
File:K7SF7D3301V1 02.png|
File:K7SF7D3301V1 03.png|
File:K7SF7D3301V1 01.png|
File:K7SF7D3301V1 05.png|
File:K7SF7D3301V1 06.png|
File:K7SF7D3301V1 07.png|
File:K7SF7D3301V1 08.png|
File:K7SF7D3301V1 03.png|
File:K7SF7D3301V1 10.png|
File:K7SF7D3301V1 11.png|
File:K7SF7D3301V1 12.png|
File:K7SF7D3301V1 13.png|
File:K7SF7D3301V1 14.png|
File:K7SF7D3301V1 15.png|
File:K7SF7D3301V1 16.png|
File:K7SF7D3301V1 17.png|
File:K7SF7D3301V1 18.png|
File:K7SF7D3301V1 19.png|
File:K7SF7D3301V1 20.png|
File:K7SF7D3301V1 21.png|
File:K7SF7D3301V1 22.png|
File:K7SF7D3301V1 23.png|
File:K7SF7D3301V1 24.png|
File:K7SF7D3301V1 25.png|
File:K7SF7D3301V1 26.png|
File:K7SF7D3301V1 27.png|
File:K7SF7D3301V1 28.png|
File:K7SF7D3301V1 29.png|
File:K7SF7D3301V1 30.png|
File:K7SF7D3301V1 31.png|
File:K7SF7D3301V1 32.png|
&lt;/gallery&gt;&lt;/center&gt;[[Has images::fcc| ]]

[[Category:English Documentation]]</text>
      <sha1>aefyfiuo146hei070wpzk8hurhobi9g</sha1>
    </revision>
  </page>