<page>
    <title>Belkin F5U215-MOB v2</title>
    <ns>0</ns>
    <id>10087</id>
    <revision>
      <id>362576</id>
      <parentid>344383</parentid>
      <timestamp>2024-04-04T22:25:57Z</timestamp>
      <contributor>
        <username>DarkShadow</username>
        <id>3096572</id>
      </contributor>
      <comment>fixed:)</comment>
      <origin>362576</origin>
      <model>wikitext</model>
      <format>text/x-wiki</format>
      <text bytes="3314" sha1="lx1khb5x8ulca2r7e0hiz22l4cnd4di" xml:space="preserve">{{Infobox USB Hub
|image1             = &lt;!-- Image filename --&gt;
|image1_size        = &lt;!-- Image size, ex.150px --&gt;
|caption            = Hi-Speed USB 2.0 Mini Hub
|caption2           = &lt;!-- 2nd tagleine --&gt;
|pp                 = &lt;!-- product page url only --&gt;
|sp                 = &lt;!-- Support page url only --&gt;
|dl                 = &lt;!-- Download page url only --&gt;
|wikidevi           = &lt;!-- wikidevi.wi-cat.ru page, included underscores --&gt;
|wikipedia          = &lt;!-- [[wikipedia:Main Page|Wikipedia]] Leave blank for none --&gt;

|brand              = Belkin
|model              = F5U215-MOB
|submodelappend     = &lt;!-- yes, for space --&gt;
|submodel           = &lt;!-- SubModel number, Leave blank for unknown --&gt;
|revision           = v2
|subrevision        = &lt;!-- Model Subrevision, Leave blank for none or unknown --&gt;
|model_part_num     = 
|page_start_date    = 04/29/2013
|page_start_origon  = https://wikidevi.com/wiki/Belkin_F5U215-MOB_v2
|sernum             = &lt;!-- Serial number prefix --&gt;
|series             = &lt;!-- Device series --&gt;

|usb_ver            = 2.0
|conn               = Male A
|size_class         = mini

|vendor_id          = 058f
|device_id          = 6254
|vendor_id2         = &lt;!-- Leave blank for none --&gt;
|device_id2         = &lt;!-- Leave blank for none --&gt;
|fcc_id             = &lt;!-- Federal Communication Commission Identification Number --&gt;

|controller_num     = &lt;!-- Number of controllers --&gt;
|chip1              = Alcor Micro;AU6254;
|chip2              = &lt;!-- Brand;Model;Extra, info; --&gt;
|chip3              = &lt;!-- Brand;Model;Extra, info; --&gt;
|chip4              = &lt;!-- Brand;Model;Extra, info; --&gt;

|pwr_optional       = true
|pwr_volt_type      = &lt;!-- VDC,VAC or POE --&gt;
|pwr_vdc            = 5
|pwr_amp_dc         = 2.1
|pwr_conn           = barrel
|pwr_barrel_outer   = &lt;!-- Outer barrel size in mm --&gt;
|pwr_barrel_inner   = &lt;!-- Inner barrel size in mm --&gt;
|pwr_barrel_len     = &lt;!-- Length of barrel --&gt;
|pwr_pol            = &lt;!-- Connector polarity --&gt;

|ports              = 4
|tt                 = single
|power_led          = red
|port_led           = 
|flags              = &lt;!-- Leave blank for none --&gt;

|is_manuf           = &lt;!-- Yes, or No, --&gt;
|manuf              = &lt;!-- Manufacturer --&gt;
|manuf_model        = &lt;!-- Manufacturer Model --&gt;
|manuf_rev          = &lt;!-- Manufacturer Revision --&gt;

|availability       = &lt;!-- Market availability --&gt;
|eoldate            = &lt;!-- End of Life date --&gt;
|estreldate         = &lt;!-- Estimated release date --&gt;
|estprice           = &lt;!-- Estimated retail price in US dollars --&gt;
|upc                = 722868531174
|ean                = &lt;!-- EAN number --&gt;
|dx_sku             = &lt;!-- DealExtreme sku --&gt;
|newegg             = &lt;!-- newegg item number --&gt;
|asin               = B0006ZKDJC
|asin_country       = &lt;!-- ASIN country --&gt;
|asin2              = &lt;!-- ASIN number --&gt;
|asin_country2      = &lt;!-- ASIN country --&gt;
|countrymanuf       = China

}}{{TIDTOC|adapter}}
==Overview==
&quot;F5U215-AU REV:1.3/1.6mm&quot; is silkscreened on the board.
:The '''[[Alcor Micro]]''' Hub IC package is marked with &quot;ALCOR&quot;, &quot;AU6254&quot;, &quot;M41-JBL-GR&quot;, &quot;H49914-1F&quot;, and &quot;1003T6E1&quot;.

The S/N of the hub used to populate this entry is '''C40'''''1513611''. This is presumed to be the v2 unit.. but that may not be accurate..

[[Category:English Documentation]]</text>
      <sha1>lx1khb5x8ulca2r7e0hiz22l4cnd4di</sha1>
    </revision>
  </page>