<page>
    <title>Foxconn J20H081</title>
    <ns>0</ns>
    <id>11356</id>
    <revision>
      <id>353918</id>
      <parentid>340141</parentid>
      <timestamp>2024-03-21T07:20:37Z</timestamp>
      <contributor>
        <username>DarkShadow</username>
        <id>3096572</id>
      </contributor>
      <comment>add data</comment>
      <origin>353918</origin>
      <model>wikitext</model>
      <format>text/x-wiki</format>
      <text bytes="4211" sha1="3an0gmf5t1cusvf16j7f753kquzk0na" xml:space="preserve">{{Infobox Network Adapter
|image1             = &lt;!-- Image filename --&gt;
|image1_size        = &lt;!-- Image size, ex.150px --&gt;
|caption            = &lt;!-- tagline --&gt;
|caption2           = &lt;!-- 2nd tagleine --&gt;
|pp                 = &lt;!-- product page url only --&gt;
|sp                 = &lt;!-- Support page url only --&gt;
|dl                 = &lt;!-- Download page url only --&gt;
|wikidevi           = Foxconn_J20H081
|wikipedia          = &lt;!-- [[wikipedia:Main Page|Wikipedia]] Leave blank for none --&gt;

|brand              = Foxconn
|model              = J20H081
|submodelappend     = &lt;!-- yes for space --&gt;
|submodel           = &lt;!-- SubModel number, Leave blank for unknown --&gt;
|revision           = &lt;!-- Model Revision, Leave blank for none or unknown --&gt;
|subrevision        = &lt;!-- Model Subrevision, Leave blank for none or unknown --&gt;
|model_part_num     = 
|page_start_date    = 12/31/2013
|page_start_origon  = https://wikidevi.com/wiki/Foxconn_J20H081
|sernum             = &lt;!-- Serial number prefix --&gt;
|wlclass            = AC600
|series             = &lt;!-- Device series --&gt;
|if                 = USB
|if_bus_version     = 2.0
|ifconnector        = JST SM05B-GHS-TB (non-standard connector)
|formfactor         = module

|vendor_id          = &lt;!-- Leave blank for none --&gt;
|device_id          = &lt;!-- Leave blank for none --&gt;
|subvendor_id       = &lt;!-- Leave blank for none --&gt;
|subdevice_id       = &lt;!-- Leave blank for none --&gt;
|id_string          = &lt;!-- PnP ID string --&gt;
|windosid           = &lt;!-- Windows ID, Leave blank for none --&gt;
|fcc_id             = MCLJ20H081
|icid               = 2878D-J20H081
|boardid            = &lt;!-- Board ID --&gt;
|ecc_id             = &lt;!-- eec-id --&gt;
|oui                = 80:56:F2

|chip1              = MediaTek;MT7650U;MT7650UN, 1325-AMAL, DTPNP857;
|chip2              = &lt;!-- Brand;Model;Extra, info; --&gt;
|chip3              = &lt;!-- Brand;Model;Extra, info; --&gt;
|chip4              = &lt;!-- Brand;Model;Extra, info; --&gt;

|antconn            = &lt;!-- Leave blank for unknown --&gt;
|antenna            = &lt;!-- Antenna type --&gt;
|txchains           = 1
|rxchains           = 1
|sstreams           = 1
|wirelessstand      = IEEE 802.11a/b/g/n/ac
|802.11ac           = 433
|802.11n            = 150/150
|802.11g            = 54
|802.11b            = 11
|802.11a            = 54
|wififreq           = 2.4 or 5
|receive_sens       = &lt;!-- Receive sensitivity --&gt;
|transmit_power     = &lt;!-- Transmit power --&gt;

|linuxdriv          = mt7610u
|windriv            = 

|is_manuf           = No
|manuf              = &lt;!-- Manufacturer --&gt;
|manuf_model        = &lt;!-- Manufacturer Model --&gt;
|manuf_rev          = &lt;!-- Manufacturer Revision --&gt;
|addchip            = 5 GHz Front-End Module;Skyworks;SKY85703-11;SKY11, 85703, 303UY;1;
|flags              = Bluetooth 3.0+EDR
|802dot11_protocols = abgn+ac
|accessible_UART    = No
|accessible_JTAG    = 
|category           = 

|availability       = &lt;!-- Market availability --&gt;
|eoldate            = &lt;!-- End of Life date --&gt;
|fccapprovdate      = 10/25/2013
|estreldate         = &lt;!-- Estimated release date --&gt;
|estprice           = &lt;!-- Estimated retail price in US dollars --&gt;
|upc                = &lt;!-- UPC number --&gt;
|ean                = &lt;!-- EAN number --&gt;
|dx_sku             = &lt;!-- DealExtreme sku --&gt;
|newegg             = &lt;!-- newegg item number --&gt;
|asin               = &lt;!-- ASIN number --&gt;
|asin_country       = &lt;!-- ASIN country --&gt;
|asin2              = &lt;!-- ASIN number --&gt;
|asin_country2      = &lt;!-- ASIN country --&gt;
|country            = China

|powledcolor        = &lt;!-- Led colors and descriptions --&gt;
|connactled         = &lt;!-- Led colors and descriptions --&gt;
|spdledcolor        = &lt;!-- Led colors and descriptions --&gt;
|leddupcolor        = &lt;!-- Led colors and descriptions --&gt;
|dimmin             = &lt;!-- Size of device --&gt;
|weight             = &lt;!-- Weight of device --&gt;

}}{{TIDTOC|adapter}}
==Overview==
*&quot;Model: J20H081&quot;, &quot;FCC ID: MCLJ20H081&quot;, &quot;IC: 2878D-J20H081&quot;, &quot;J20H081&quot;, &quot;801489&quot;, &quot;REV.0 GP&quot;, and a date code of '''1337''' is silkscreened on the board in the FCC photos.

A MAC label affixed to the device indicates usage of a 80:56:F2 ('''Hon Hai''') OUI. It's presumed to be used.

[[Category:English Documentation]]</text>
      <sha1>3an0gmf5t1cusvf16j7f753kquzk0na</sha1>
    </revision>
  </page>