<page>
    <title>Gigabyte GN-WB32L-RH</title>
    <ns>0</ns>
    <id>23300</id>
    <revision>
      <id>369160</id>
      <parentid>340396</parentid>
      <timestamp>2024-06-22T13:19:51Z</timestamp>
      <contributor>
        <username>DarkShadow</username>
        <id>3096572</id>
      </contributor>
      <comment>add data</comment>
      <origin>369160</origin>
      <model>wikitext</model>
      <format>text/x-wiki</format>
      <text bytes="3901" sha1="7l0bqdjnu424p8uobw087qa2g1cuwn5" xml:space="preserve">{{Infobox Network Adapter
|image1             = Gigabyte GN-WB32L-RH.jpg
|image1_size        = 50px
|caption            = AirCruiser Ultra N USB Adapter
|caption2           = &lt;!-- 2nd tagleine --&gt;
|pp                 = https://www.gigabyte.com/Enterprise/Wireless-Product/GN-WB32L-rev-10
|sp                 = &lt;!-- Support page url only --&gt;
|dl                 = &lt;!-- Download page url only --&gt;
|wikidevi           = &lt;!-- wikidevi.wi-cat.ru page, included underscores --&gt;
|wikipedia          = &lt;!-- [[wikipedia:Main Page|Wikipedia]] Leave blank for none --&gt;

|brand              = Gigabyte
|model              = GN-WB32L-RH
|submodelappend     = &lt;!-- yes for space --&gt;
|submodel           = &lt;!-- SubModel number, Leave blank for unknown --&gt;
|revision           = &lt;!-- Model Revision, Leave blank for none or unknown --&gt;
|subrevision        = &lt;!-- Model Subrevision, Leave blank for none or unknown --&gt;
|model_part_num     = 
|page_start_date    = June 16, 2010 
|page_start_origon  = https://wikidevi.com/wiki/Gigabyte_GN-WB32L-RH
|sernum             = &lt;!-- Serial number prefix --&gt;
|wlclass            = N150
|series             = &lt;!-- Device series --&gt;
|if                 = USB
|if_bus_version     = 2.0
|ifconnector        = Male A
|formfactor         = dongle

|vendor_id          = 1044
|device_id          = 800d
|subvendor_id       = &lt;!-- Leave blank for none --&gt;
|subdevice_id       = &lt;!-- Leave blank for none --&gt;
|id_string          = &lt;!-- PnP ID string --&gt;
|windosid           = &lt;!-- Windows ID, Leave blank for none --&gt;
|fcc_id             = JCK-GN-WB32L-RH
|icid               = &lt;!-- Industry Canada ID, Leave blank for none --&gt;
|boardid            = &lt;!-- Board ID --&gt;
|ecc_id             = &lt;!-- eec-id --&gt;
|oui                = 6C:F0:49

|chip1              = Ralink;RT3070;
|chip2              = &lt;!-- Brand;Model;Extra, info; --&gt;
|chip3              = &lt;!-- Brand;Model;Extra, info; --&gt;
|chip4              = &lt;!-- Brand;Model;Extra, info; --&gt;

|antconn            = U.FL
|antenna            = &lt;!-- Antenna type --&gt;
|txchains           = 1
|rxchains           = 1
|sstreams           = 1
|wirelessstand      = IEEE 802.11b/g/n
|802.11n            = 150
|802.11g            = 54
|802.11b            = 11
|wififreq           = 2.4
|receive_sens       = &lt;!-- Receive sensitivity --&gt;
|transmit_power     = &lt;!-- Transmit power --&gt;

|linuxdriv          = 
|windriv            = 

|is_manuf           = &lt;!-- Yes, or No, --&gt;
|manuf              = &lt;!-- Manufacturer --&gt;
|manuf_model        = &lt;!-- Manufacturer Model --&gt;
|manuf_rev          = &lt;!-- Manufacturer Revision --&gt;
|addchip            = &lt;!-- Additional Chips --&gt;
|flags              = translucent case
|802dot11_protocols = bgn
|accessible_UART    = No
|accessible_JTAG    = 
|category           = 

|availability       = &lt;!-- Market availability --&gt;
|eoldate            = &lt;!-- End of Life date --&gt;
|fccapprovdate      = 04/02/2009
|estreldate         = &lt;!-- Estimated release date --&gt;
|estprice           = &lt;!-- Estimated retail price in US dollars --&gt;
|upc                = &lt;!-- UPC number --&gt;
|ean                = &lt;!-- EAN number --&gt;
|dx_sku             = &lt;!-- DealExtreme sku --&gt;
|newegg             = &lt;!-- newegg item number --&gt;
|asin               = &lt;!-- ASIN number --&gt;
|asin_country       = &lt;!-- ASIN country --&gt;
|asin2              = &lt;!-- ASIN number --&gt;
|asin_country2      = &lt;!-- ASIN country --&gt;
|country            = Taiwan

|powledcolor        = &lt;!-- Led colors and descriptions --&gt;
|connactled         = &lt;!-- Led colors and descriptions --&gt;
|spdledcolor        = &lt;!-- Led colors and descriptions --&gt;
|leddupcolor        = &lt;!-- Led colors and descriptions --&gt;
|dimmin             = &lt;!-- Size of device --&gt;
|weight             = &lt;!-- Weight of device --&gt;

}}{{TIDTOC|adapter}}
==Overview==
&quot;GN-WB32L-RH&quot;, &quot;Ver:0.1&quot;, and &quot;PCB MADE IN TAIWAN&quot; is silkscreened on the board in the FCC photos.

[[Category:English Documentation]]</text>
      <sha1>7l0bqdjnu424p8uobw087qa2g1cuwn5</sha1>
    </revision>
  </page>