<page>
    <title>OSBRiDGE 5G(-HP)</title>
    <ns>0</ns>
    <id>45973</id>
    <revision>
      <id>380510</id>
      <parentid>359443</parentid>
      <timestamp>2024-08-16T14:30:59Z</timestamp>
      <contributor>
        <username>ShadowBot</username>
        <id>3357272</id>
      </contributor>
      <minor/>
      <comment>/* top */clean up</comment>
      <origin>380510</origin>
      <model>wikitext</model>
      <format>text/x-wiki</format>
      <text bytes="15524" sha1="18n7aia1shjdtonam216qssud3a1c1v" xml:space="preserve">{{Infobox Embedded System
|image1             = &lt;!-- Image filename --&gt;
|image1_size        = &lt;!-- Image size, ex.150px --&gt;
|caption            = 5GHz Outdoor Base Station
|caption2           = &lt;!-- 2nd tagleine --&gt;
|pp                 = &lt;!-- product page url only --&gt;
|sp                 = &lt;!-- Support page url only --&gt;
|dl                 = &lt;!-- Download page url only --&gt;
|fandom             = OSBRiDGE_5G(-HP)
|wikidevi           = &lt;!-- wikidevi.wi-cat.ru page, included underscores --&gt;
|wikipedia          = &lt;!-- [[wikipedia:Main Page|Wikipedia]] Leave blank for none --&gt;
|ddwrtsupport       = &lt;!-- Activation, Donation, Incompatible, Not Supported, Partial Support, Supported, TBD, Unofficially, WIP --&gt;
|openwrtsupport     = &lt;!-- Incompatible, Not Supported, Partial Support, Supported, WIP, Unofficially, --&gt;
|tomatosupport      = &lt;!-- Incompatible, Not Supported, Partial Support, Supported, WIP, Unofficially, --&gt;
|gargoylesupport    = &lt;!-- Incompatible, Not Supported, Partial Support, Supported, WIP, Unofficially, --&gt;

|brand              = OSBRiDGE
|model              = 5G
|submodelappend     = &lt;!-- yes, for space --&gt;
|submodel           = -HP
|revision           = &lt;!-- Model Revision, Leave blank for none or unknown --&gt;
|subrevision        = &lt;!-- Model Subrevision, Leave blank for none or unknown --&gt;
|model_part_num     = 
|page_start_date    = 12/04/2010 
|page_start_origon  = https://infodepot.fandom.com/wiki/OSBRiDGE_5G(-HP)
|wlclass            = A108
|series             = &lt;!-- Device series --&gt;
|type               = access point
|sernum             = &lt;!-- First 4 or so for easy version identification --&gt;
|fcc_id             = &lt;!-- Federal Communication Commission Identification Number --&gt;
|icid               = &lt;!-- Industry Canada Identification number, Leave blank for unknown --&gt;
|us_id              = &lt;!-- US ID number --&gt;
|boardid            = &lt;!-- Board Identification, Leave blank for none --&gt;
|ecc_id             = &lt;!-- eec-id --&gt;

|cpu1chip1          = Intel XScale;IXP425;
|cpu1_cores         = &lt;!-- 1,2,3,4 --&gt;
|cpu1_type          = &lt;!-- ARM,MIPS,x86-64, --&gt;
|cpu1_type_rev      = &lt;!-- CPU1 type Revision, Leave blank for unknown --&gt;
|cpu1spd            = 533 &lt;!--  --&gt;
|is_doc             = 
|bus                = &lt;!-- 8-bit, 16-bit, 32-bit, 64-bit, Leave blank for none --&gt;

|flash1type         = &lt;!-- Parallel,Serial(SPI),SPI NOR,NAND,Compact Flash, --&gt;
|fla1_num           = &lt;!-- 1,2,3,4 --&gt;
|fla1chip           = &lt;!-- Brand;Model;Extra, info; --&gt;
|flash1size         = 4
|flash1maxsize      = &lt;!-- Maximum size firmware can be in bytes --&gt;

|ram1type           = &lt;!-- DDR,DDR2,DDR3,DDR4, --&gt;
|ram1type1          = &lt;!-- SO-DIMM,SDRAM, --&gt;
|ram1spd            = &lt;!-- RAM speed --&gt;
|ram1size           = 64
|ram1chip           = &lt;!-- Brand;Model;Extra, info; --&gt;
|ram1_num           = &lt;!-- Number of Ram chips --&gt;
|nvramsize          = &lt;!-- 32, 60, 64, etc... in kb, Leave blank for unknown --&gt;

|eth_cpu            = &lt;!-- true, --&gt;
|eth1chip           = &lt;!-- Brand;Model;Extra, info; --&gt;
|eth2chip           = &lt;!-- Brand;Model;Extra, info; --&gt;
|eth3chip           = &lt;!-- Brand;Model;Extra, info; --&gt;
|eth4chip           = &lt;!-- Brand;Model;Extra, info; --&gt;
|sw_cpu             = &lt;!-- true, --&gt;
|sw1chip            = &lt;!-- Brand;Model;Extra, info; --&gt;
|wan_ports          = &lt;!-- 1, --&gt;
|wan_speed          = &lt;!-- 10MbE,100MbE,1GbE, --&gt;
|lan_ports          = 1
|lan_speed          = 100MbE
|ethstandard        = IEEE 802.3/3u
|auto_mdix          = &lt;!-- mdix support --&gt;
|sup_jumbo          = &lt;!-- Jumbo frames support --&gt;
|ethoui             = &lt;!-- Leave blank for unknown --&gt;
|oui                = &lt;!-- Wireless OUI --&gt;

|bootwait           = &lt;!-- On or Off, Leave blank for unknown --&gt;
|stockbootloader    = &lt;!-- Name;Version;Distro --&gt;
|stockos            = &lt;!-- Name;Version;Distro --&gt;

|exp_if_types       = Mini PCI
|exp_sim_num        = &lt;!-- Number of sim Slots, Leave blank for none --&gt;
|exp_pcmcia_num     = &lt;!-- Number of pcmcia ports, Leave blank for none --&gt;
|exp_expcard_num    = &lt;!-- Number of Expresscard ports, Leave blank for none --&gt;
|exp_minipci_num    = 2
|exp_minipcie_num   = &lt;!-- Number of Mini PCIexpress Slots, Leave blank for none --&gt;
|exp_usb_num        = &lt;!-- Number of USB Ports, Leave blank for none --&gt;
|exp_cf_num         = &lt;!-- Number Compact Flash Slots, Leave blank for none --&gt;
|exp_sdmmc_num      = &lt;!-- Number SD/MMC Slots, Leave blank for none --&gt;
|exp_ide_num        = &lt;!-- Number of ide ports, Leave blank for none --&gt;
|exp_ata_num        = &lt;!-- Number of ATA Ports, Leave blank for none --&gt;
|exp_sata_num       = &lt;!-- Number of sata ports, Leave blank for none --&gt;
|exp_esata_num      = &lt;!-- Number of esata ports, Leave blank for none --&gt;
|exp_parallel       = &lt;!-- Number of parallel ports, Leave blank for none --&gt;
|exp_sfp_num        = &lt;!-- Number of sfp ports, Leave blank for none --&gt;
|exp_M.2            = &lt;!-- Number of M.2 ports, Leave blank for none --&gt;
|exp_hdmi_num       = 
|usb_hub            = &lt;!-- USB hub compatibility --&gt;

|pwr_volt_type      = POE
|pwr_vdc            = &lt;!-- DC Volts --&gt;
|pwr_amp_dc         = &lt;!-- DC Amps --&gt;
|pwr_poe_type       = af
|pwr_poe            = 48
|pwr_poe_amp        = 0.4
|pwr_conn           = Ethernet (PoE)

|serial             = &lt;!-- Full Serial info --&gt;
|jtag               = &lt;!-- Full JTAG info --&gt;

|specialfeat        = &lt;!-- Features that don't fit any place else, Leave blank for none --&gt;
|flags              = &lt;!-- flags, Leave blank for none --&gt;
|addchip            = &lt;!-- Additional Chips --&gt;
|802dot11_protocols = a

|defaulip           = &lt;!-- ???.???.???.???, default IP Address --&gt;
|defaultlogin       = &lt;!-- default Login Name, Leave blank for unknown --&gt;
|defaultpass        = &lt;!-- default Password, Leave blank for unknown --&gt;
|defaultssid        = &lt;!-- default Wireless ID, Leave blank for unknown --&gt;
|defaultssid_regex  = 
|default_ch         = &lt;!-- Defaults channel(s) Radio(s) are set to --&gt;
|manuf              = &lt;!-- Manufacturer --&gt;
|manuf_model        = &lt;!-- Manufacturer Model --&gt;
|manuf_rev          = &lt;!-- Manufacturer Revision --&gt;
|is_manuf           = &lt;!-- Yes, or No, --&gt;
|tpfirmware         = &lt;!-- Third party firmware official support, AsusWRT-Merlin, CeroWrt, DD-WRT, DD-WRT (kong), DD-WRT (kongac), DD-WRT (kongarm), FreedomBox, FreshTomato-ARM, Gargoyle, LibreWrt, Oleg (wl500g), Oleg-ng (wl500g), OpenWrt, Tomato, Tomato RAF, Tomato (shibby), Tomato (Toastman), TomatoUSB, Wive-NG --&gt;

|availability       = &lt;!-- Market availability --&gt;
|eoldate            = &lt;!-- End of Life date --&gt;
|fccapprovdate      = &lt;!-- FCCID approval date --&gt;
|estreldate         = &lt;!-- Estimated release date --&gt;
|estprice           = &lt;!-- Estimated retail price in US dollars --&gt;
|upc                = &lt;!-- UPC number --&gt;
|ean                = &lt;!-- EAN number --&gt;
|dx_sku             = &lt;!-- DealExtreme sku --&gt;
|newegg             = &lt;!-- newegg item number --&gt;
|asin               = &lt;!-- ASIN number --&gt;
|asin_country       = &lt;!-- ASIN country --&gt;
|asin2              = &lt;!-- ASIN number --&gt;
|asin_country2      = &lt;!-- ASIN country --&gt;
|countrymanuf       = &lt;!-- Country device was manufactured in --&gt;

|buttons            = &lt;!-- buttons available --&gt;
|led                = &lt;!-- Led colors and descriptions --&gt;
|dimensions         = 280 mm X 180 mm X 60 mm
|weight             = &lt;!-- Weight of device {{convert|weight|oz|g}} --&gt;

|wi1_if_name        = 
|rad1mod            = &lt;!-- Radio module name, optional link, Leave blank for none --&gt;
|rad1modif          = &lt;!-- Radio Module Interface Type, Leave blank for none --&gt;
|rad1chip1          = Atheros;AR5006XS;
|rad1oui            = &lt;!-- Only if different from above OUI --&gt;
|rad1_ant_conn      = &lt;!-- Leave blank for unknown --&gt;
|rad1stand          = IEEE 802.11a
|rad1a              = 54
|rad1freq           = 5

|wi2_if_name        = 
|rad2mod            = &lt;!-- Radio module name, optional link, Leave blank for none --&gt;
|rad2modif          = &lt;!-- Radio Module Interface Type, Leave blank for none --&gt;
|wi2_if_name        = 
|rad2chip1          = Atheros;AR5006XS;
|rad2oui            = &lt;!-- Only if different from above OUI --&gt;
|rad2_ant_conn      = &lt;!-- Leave blank for unknown --&gt;
|rad2stand          = IEEE 802.11a
|rad2a              = 54
|rad2freq           = 5

}}{{TIDTOC|embedded}}
==Overview==
OSBRiDGE 5G-HP 5GHz Outdoor Base Station

The OSBRiDGE 5G, a member of OSBRiDGE products family, is a high performance 5GHz outdoor wireless Access Point designed to provide secure and reliable point to multipoint operation for Carriers, Internet Service Providers, Business Enterprises and Government organisations.

=== Performance ===

The OSBRiDGE 5G is capable of supporting up to 108 Mbps over each of its two air interfaces, equivalent to 70 Mbps Net Throughput'. The OSBRiDGE 5G leverages both robust outdoor technologies and Orthogonal Frequency Division Multiplexing (OFDM) modulation in the same product - with features such as Forward Error Correction coding, used to combat multi-path and noisy environments, the product operates seamlessly and efficiently in challenging environments with stable throughput. The system also features advanced algorithms for automatic selection of modulation schemes to maximize the data rate and improve spectral efficiency using latest technology based on Atheros® AR5006XS Radio Modules. These inherent advantages of the OSBRIDGE 5G enable service providers to provide an effective PtMP solution to a significantly higher subscriber base that would otherwise be inaccessible.

=== Capability ===

Each OSBRiDGE 5G system can handle many wireless subscribers per cell, whether they're spread out or live in densely populated neighborhoods. Combining high frequency reuse, selectable channel width with advanced interference management and immunity techniques, the OSBRiDGE 5G system conserves valuable spectrum by allowing the service provider to cover an extensive geographical area with a minimum number of channels. As bandwidth and subscriber needs increase, network operators can easily add channels or new sectors within the cell. Operators can also economically deploy additional cells to extend the service capacity and coverage footprint.

=== Compatibility ===

While operating with OSBRiDGE CPE devices family (5XLi, 5GXi) the OSBRiDGE 5G device can be configured to utilize proprietary polling protocol that overrides shortages of the standard 802.11a mode. OSBRiDGE proprietary WPM (Wireless Polling MAC) is a full featured TDMATTDD protocol implementation on top of Atheros® AR5006XS hardware, using Packet Aggregation, Adaptive Polling Algorithm and disabling of the CSMA Backoff Mechanism. WPM also provides link adaptation technology and improves bandwidth, robustness, and overall performance for each subscriber.

=== Technology ===

OSBRiDGE 5G based on superior Intel XScale IXP425 processor clocked at 533MHz easily outperforms other devices based on alternative chipsets. Intel® IXP425 network processor is a highly integrated, versatile single-chip processor that is used in a variety of products that require network connectivity and high performance to run their unique software applications. Each processor combines a high-performance Intel XScale® core with additional Network Processor Engines (NPEs) to achieve unmatched packet processing performance.

=== Durability ===

All OSBRiDGE 5G products are robust, IP65 rated, outdoor units, that are built to perform in difficult climatic environments and withstand even the harshest weather conditions. Built in 802.3af compliant Power over Ethernet system allows only one ethernet cable to be used for both data and power transmission for up to for up to 305 feet.

=== Highlights ===

    Licence Exempt ETSI and FCC 5GHz
    Frequency— eliminates regulatory delays.
    11 (ETSI), 4 (United Kingdom), 5 (USA) and 236 (Unregulated Countries) non-overlaping channels allows many units to be deployed in the same area.
    User Selectable channel width — 5 MHz, 10 MHz, 20 MHz or 40 MHz for scalable deployment and interference resiliency.
    Next day deployment enables rapid service activation and payback.
    Up to 70 Mbps of effective TCP/IP throughput per sector in 40 MHz channel mode, while proprietary protocol enhancements assure effective and robust transmission ranges of up to 30 miles.
    Cost effective alternative to leased lines.
    Optimal cost / performance ratio: highly cost efficient solution.
    Dynamic Frequency Selection (DFS) complies with ETSI EN 301 893 and OFCOM regulations to allow co-existence with Radar systems.
    Robust outdoor architecture: ensures unprecedented range and reliability, minimizes RF cable loss connecting to antenna thus providig outstanding performance and communication distance.
    Superior Atheros XRTM AR5006XS powered OFDM radio — enables NLOS (near line of sight) operation in dense urban environments.
    Non-compromising security - over the air 128bit keyAES encryption.
    Compatible with other vendors 802.11a compliant devices.

=== Wired Interface ===

    Ethernet Interface: 100 base-T Ethernet (RJ-45) with PoE
    Wired LAN Protocol: IEEE 802.3 (CSMA/CD)
    Wireless Interface: Two N Female Connectors for external Antennas, 50 Ohms
    Wireless LAN Protocol: User Configurable - IEEE 802.11a or WPM (Wireless Polling MAC)

=== Radio - Two Wireless Interfaces ===

    Supported Frequencies
        UK (OFCOM FWA): 5735 - 5835 MHz (4 channels) with DFS (Dynamic Frequency Selection)
        Europe (ETSI): 5500 - 5700 MHz (11 channels) with DFS (Dynamic Frequency Selection)
        USA (FCC): 5745 - 5825 MHz (5 channels)
        Africa &amp; Asia (OTHER): 4920 - 6100 MHz (236 channels, 5 MHz step)
    Modulation Technique: BPSK, QPSK, 16QAM, 64QAM
    Channel Width: User Selectable: 802.11a: 20 MHz, 10 MHz, 5 MHz or 40 MHz (802.11a Turbo)
    Bit Error Rate (BER): Better than 10
    Output Power: +25dBm
    Receive Threshold at 20MHz channel (dBm)
        -88 @ 18Mbps
        -89 @ 12Mbps
        -90 @ 9Mbps
        -92 @ 6Mbps
    Receive Threshold at 10MHz channel (dBm)
        -88 @ 9Mbps
        -89 @ 6Mbps
        -90 @ 4.5Mbps
        -92 @ 3Mbps
    Receive Threshold at 5MHz channel (dBm)
        -88 @ 4.5Mbps
        -89 @ 3Mbps
        -90 @ 2.25Mbps
        -92 @ 1.5Mbps

=== System ===

    Processor: Intel XScale IXP425 533MHz Network Processor
    Memory: 64MB RAM, 4MB Flash
    RF Modules: Two Independent Atheros AR5006X Radio Interfaces

=== Software ===

    Operational Modes: Access Point, WPM Base
    Security: Association Protocol – ESSID/BSSID, WEP 40/128, TKIP, AES
    Features: Bridge, Router, Router, Firewall, QOS
    Management: WEB Interface, SNMPv2

=== Physical ===

    Dimensions: 280 mm X 180 mm X 60 mm
    Operating / Storage Temperature: -40°C - +70°C / -40°C - +85°C
    Enclosure: Aluminium, IP65 Rated, UV Protected, Outdoor Mountable, Weather Protected
    Power Adapter: 48V/0.4A DC, 802.3af Active Ethernet (Power over Ethernet injector included)
    LEDs: 2 – Power, Ethernet LAN
    Mounting: Flexible Pole Mounting

=== Dedicated Antennas ===

    Sector Antenna, Vertical Polarization, 14dBi, 90°/6° HN

=== Operational Distance (m) ===

    10200 @ 54Mbps
    11400 @ 48Mbps
    13000 @ 36Mbps
    14200 @ 24Mbps
    15200 @ 18Mbps
    17000 @ 12Mbps
    19200 @ 9Mbps
    23000 @ 6Mbps

=== Regulatory Compliance ===

    CE mark, ETSI EN301 893 Compliant, FCC Part 15 Compliant, RoHS Compliant

[[Category:English Documentation]]</text>
      <sha1>18n7aia1shjdtonam216qssud3a1c1v</sha1>
    </revision>
  </page>