{
    "modular": false,
    "data": [
        {
            "url": "https://fcc.report//FCC-ID/KA2WBR2310B1/939437.pdf",
            "name": "939437.pdf",
            "type": "Cover Letter(s)",
            "description": "Agency Agreement 2",
            "date": "2008-05-09",
            "sha256": "1a29edea1d51c2870a615ab069681e963b81522e9fa956c5c721b1350f52eac0"
        },
        {
            "url": "https://fcc.report//FCC-ID/KA2WBR2310B1/939436.pdf",
            "name": "939436.pdf",
            "type": "Cover Letter(s)",
            "description": "Agency Agreement 1",
            "date": "2008-05-09",
            "sha256": "e59c63887b8e23fa3c4bc0862cd38285bde9ffcf3d23b857239cf658e71a5d98"
        },
        {
            "url": "https://fcc.report//FCC-ID/KA2WBR2310B1/939435.pdf",
            "name": "939435.pdf",
            "type": "Cover Letter(s)",
            "description": "Confidentiality Request",
            "date": "2008-05-09",
            "sha256": "9a7700e1edd74d8d6c0366e8c4561bc1c7b803478cf804e3f4ecb6149e153018"
        },
        {
            "url": "https://fcc.report//FCC-ID/KA2WBR2310B1/939434.pdf",
            "name": "939434.pdf",
            "type": "Attestation Statements",
            "description": "Ad hoc declaration",
            "date": "2008-05-09",
            "sha256": "84faaf8a2977408a930d61b17a75068082871b7b546ce91fa99be906aa7a0414"
        },
        {
            "url": "https://fcc.report//FCC-ID/KA2WBR2310B1/939417.pdf",
            "name": "939417.pdf",
            "type": "RF Exposure Info",
            "description": "RF Exposure Info",
            "date": "2008-05-09",
            "sha256": "457cb08c1ead7c5154c58b471215ed200952e36797514a578989a02dab0ace02"
        },
        {
            "url": "https://fcc.report//FCC-ID/KA2WBR2310B1/939416.pdf",
            "name": "939416.pdf",
            "type": "Users Manual",
            "description": "Manual",
            "date": "2008-05-09",
            "sha256": "0534131584c99a40fa8d49751697f7310b47b441c06adec3b815657301e2328a"
        },
        {
            "url": "https://fcc.report//FCC-ID/KA2WBR2310B1/939415.pdf",
            "name": "939415.pdf",
            "type": "Test Setup Photos",
            "description": "Test Setup Photos",
            "date": "2008-05-09",
            "sha256": "acacdbf00a1eeb446e78621aa69dbf64a5516be8871a2a5bb37aa78aabf2ef32"
        },
        {
            "url": "https://fcc.report//FCC-ID/KA2WBR2310B1/939414.pdf",
            "name": "939414.pdf",
            "type": "Test Report",
            "description": "Test Report",
            "date": "2008-05-09",
            "sha256": "7be8308de20a5b5c0595c2afbfc1f3774110970dd7317ed6f99111be6a33e312"
        },
        {
            "url": "https://fcc.report//FCC-ID/KA2WBR2310B1/939412.pdf",
            "name": "939412.pdf",
            "type": "Operational Description",
            "description": "Technical Description",
            "date": "2008-05-09",
            "sha256": "1301f53cbf26d333091f2f9f2a8e98bdff798d0a16d9a2ee0df304d861b2737d"
        },
        {
            "url": "https://fcc.report//FCC-ID/KA2WBR2310B1/939411.pdf",
            "name": "939411.pdf",
            "type": "Internal Photos",
            "description": "Internal Photos",
            "date": "2008-05-09",
            "sha256": "64cbd2103a5087419feed26f11a3c600c61ccf96dbeabd367c068a8881d9ea32"
        },
        {
            "url": "https://fcc.report//FCC-ID/KA2WBR2310B1/939410.pdf",
            "name": "939410.pdf",
            "type": "ID Label/Location Info",
            "description": "Label Location",
            "date": "2008-05-09",
            "sha256": "9a3564080e309ee6415a9915861ee169a2cfa7b69781b837e87c5a949d0e6af4"
        },
        {
            "url": "https://fcc.report//FCC-ID/KA2WBR2310B1/939409.pdf",
            "name": "939409.pdf",
            "type": "ID Label/Location Info",
            "description": "Label",
            "date": "2008-05-09",
            "sha256": "7b34a140380b5782976a86d8c12ed17035e7f1abeb7675627be95a1f86b3396b"
        },
        {
            "url": "https://fcc.report//FCC-ID/KA2WBR2310B1/939408.pdf",
            "name": "939408.pdf",
            "type": "External Photos",
            "description": "External Photos",
            "date": "2008-05-09",
            "sha256": "9b135817ec678fd59515b8364df834ea7685ec739def315e67e9c39be34c15b7"
        }
    ]
}