{
    "modular": false,
    "data": [
        {
            "url": "https://fcc.report//FCC-ID/K7SF9K1105V2/1669965.pdf",
            "name": "1669965.pdf",
            "type": "Test Setup Photos",
            "description": "test setup photos",
            "date": "2012-04-05",
            "sha256": "f9002872fa636041472a54976f2d884bf41302f09e5d0e0a244f109caa633df0"
        },
        {
            "url": "https://fcc.report//FCC-ID/K7SF9K1105V2/1669964.pdf",
            "name": "1669964.pdf",
            "type": "Test Report",
            "description": "test report",
            "date": "2012-04-05",
            "sha256": "57b7b22f9624315b99b499a7e894ced26c7d05ef7d087161c113283063764560"
        },
        {
            "url": "https://fcc.report//FCC-ID/K7SF9K1105V2/1669963.pdf",
            "name": "1669963.pdf",
            "type": "RF Exposure Info",
            "description": "MPE",
            "date": "2012-04-05",
            "sha256": "dc6cc53ab15aef52f60f956a6103fed55d39e305324640a993cbb00433ed6313"
        },
        {
            "url": "https://fcc.report//FCC-ID/K7SF9K1105V2/1669962.pdf",
            "name": "1669962.pdf",
            "type": "Cover Letter(s)",
            "description": "PoA",
            "date": "2012-04-05",
            "sha256": "32d901d5462cab4b4a215bbe735aada9bfb9c8078b1a7c7116084ba65fda2555"
        },
        {
            "url": "https://fcc.report//FCC-ID/K7SF9K1105V2/1669961.pdf",
            "name": "1669961.pdf",
            "type": "Users Manual",
            "description": "user manual",
            "date": "2012-04-05",
            "sha256": "cc3c782982024be06d1a9e8d6f5496af138ed0e3258adce0c0372cfdf63dcf62"
        },
        {
            "url": "https://fcc.report//FCC-ID/K7SF9K1105V2/1669960.pdf",
            "name": "1669960.pdf",
            "type": "ID Label/Location Info",
            "description": "label",
            "date": "2012-04-05",
            "sha256": "3f6fedd65abeb778384db97b4a935f17f5db20a8c791b6cd7c4346972435cb63"
        },
        {
            "url": "https://fcc.report//FCC-ID/K7SF9K1105V2/1669959.pdf",
            "name": "1669959.pdf",
            "type": "Internal Photos",
            "description": "internal photos",
            "date": "2012-04-05",
            "sha256": "adf781940d447be2a45735c9f4c5090089e4365d7abbac1d3370be90539111e8"
        },
        {
            "url": "https://fcc.report//FCC-ID/K7SF9K1105V2/1669958.pdf",
            "name": "1669958.pdf",
            "type": "External Photos",
            "description": "external photos",
            "date": "2012-04-05",
            "sha256": "2261e02c4f827171cfd751e965553bcb60d18856c0ddb2f8b84ee018bcb738d3"
        },
        {
            "url": "https://fcc.report//FCC-ID/K7SF9K1105V2/1669957.pdf",
            "name": "1669957.pdf",
            "type": "Cover Letter(s)",
            "description": "DoC letter",
            "date": "2012-04-05",
            "sha256": "c85ecb01a53505398591f1ef9b7c90e9ce45f1cc4bf5372f4981a2c8afafbb0d"
        },
        {
            "url": "https://fcc.report//FCC-ID/K7SF9K1105V2/1669956.pdf",
            "name": "1669956.pdf",
            "type": "Cover Letter(s)",
            "description": "request for confidentiality",
            "date": "2012-04-05",
            "sha256": "79aa3cdfcdf27da5a93e7f3f614d3b0d44233540460a908f9430ff9b7f1e9999"
        },
        {
            "url": "https://fcc.report//FCC-ID/K7SF9K1105V2/1669955.pdf",
            "name": "1669955.pdf",
            "type": "Cover Letter(s)",
            "description": "Ad Hoc Mode Function Declaration",
            "date": "2012-04-05",
            "sha256": "0b857e9cf2dfb74579f187c8251fd1fae6120fd538c7de12d76806647fedc418"
        },
        {
            "url": "https://fcc.report//FCC-ID/K7SF9K1105V2/3060734.pdf",
            "name": "3060734.pdf",
            "type": "Test Setup Photos",
            "description": "Test Setup Photos",
            "date": "2016-07-13",
            "sha256": "8bca21edb8a1078a77221532f216d5509db0ca9b67dd5621e1b1e6d700972289"
        },
        {
            "url": "https://fcc.report//FCC-ID/K7SF9K1105V2/3060733.pdf",
            "name": "3060733.pdf",
            "type": "Test Report",
            "description": "Test Report",
            "date": "2016-07-13",
            "sha256": "b9e027c6fc28583e9a772aa26272aa107ec0c1b3f4f7f5721d22591496f00ab9"
        },
        {
            "url": "https://fcc.report//FCC-ID/K7SF9K1105V2/3060732.pdf",
            "name": "3060732.pdf",
            "type": "RF Exposure Info",
            "description": "RF Exposure Test Report",
            "date": "2016-07-13",
            "sha256": "65c0af98f27fc2020f004bae0ac7e8ec098ade8464ab65f3c82026e3db17ef2a"
        },
        {
            "url": "https://fcc.report//FCC-ID/K7SF9K1105V2/3060731.pdf",
            "name": "3060731.pdf",
            "type": "Cover Letter(s)",
            "description": "POA Letter",
            "date": "2016-07-13",
            "sha256": "64e4ff482722d265c9a2b7a6dddbf02b21fda382ef5c7d09179bcc17f3d23084"
        },
        {
            "url": "https://fcc.report//FCC-ID/K7SF9K1105V2/3060730.pdf",
            "name": "3060730.pdf",
            "type": "Internal Photos",
            "description": "Internal Photos",
            "date": "2016-07-13",
            "sha256": "375f26b783d86b880960ef7f67f3f56f8907b0ff3bc23d7695241c18ce046eb5"
        },
        {
            "url": "https://fcc.report//FCC-ID/K7SF9K1105V2/3060729.pdf",
            "name": "3060729.pdf",
            "type": "External Photos",
            "description": "External Photos",
            "date": "2016-07-13",
            "sha256": "b86db8371557cf4dbeccb86a05a773977db0536e2e37ce8f1998b2fc16b5790a"
        },
        {
            "url": "https://fcc.report//FCC-ID/K7SF9K1105V2/3060728.pdf",
            "name": "3060728.pdf",
            "type": "Cover Letter(s)",
            "description": "DoC Attestation Letter",
            "date": "2016-07-13",
            "sha256": "6196f6ee1f6cc3d22a0163478114f6a045a193f0aedb72c106bf696f1ba95587"
        },
        {
            "url": "https://fcc.report//FCC-ID/K7SF9K1105V2/3060727.pdf",
            "name": "3060727.pdf",
            "type": "Cover Letter(s)",
            "description": "Confidential Letter",
            "date": "2016-07-13",
            "sha256": "b8ad20e16dd053f41e869c081e189db37e004b2b99745310b1d6ab68ae6ad61d"
        },
        {
            "url": "https://fcc.report//FCC-ID/K7SF9K1105V2/3060726.pdf",
            "name": "3060726.pdf",
            "type": "Cover Letter(s)",
            "description": "Class II Change Letter",
            "date": "2016-07-13",
            "sha256": "31037760b085a3f612460e3c526ca453ee8143bc9dc200e4a42135c76fbdbcbe"
        },
        {
            "url": "https://fcc.report//FCC-ID/K7SF9K1105V2/3060707.pdf",
            "name": "3060707.pdf",
            "type": "RF Exposure Info",
            "description": "RF Exposure Info",
            "date": "2016-07-13",
            "sha256": "cb8a1efd98e8ad1d1e0f467d73c4f990116a5f414dfdf031e3f256a7d0fac83a"
        },
        {
            "url": "https://fcc.report//FCC-ID/K7SF9K1105V2/3060706.pdf",
            "name": "3060706.pdf",
            "type": "Cover Letter(s)",
            "description": "POA",
            "date": "2016-07-13",
            "sha256": "8582198c64209fe2a5bc3ca0da70c2af2bb9b35d4e70db7e88691af0651ff786"
        },
        {
            "url": "https://fcc.report//FCC-ID/K7SF9K1105V2/3060703.pdf",
            "name": "3060703.pdf",
            "type": "Cover Letter(s)",
            "description": "DoC",
            "date": "2016-07-13",
            "sha256": "be6f23b1ac99a25f7487ba8463dc2bedf7f211a8a164bc5978f5c855a022012f"
        },
        {
            "url": "https://fcc.report//FCC-ID/K7SF9K1105V2/3060702.pdf",
            "name": "3060702.pdf",
            "type": "Cover Letter(s)",
            "description": "Confidentiality Letter",
            "date": "2016-07-13",
            "sha256": "6083b4a0cbec7234e423561102255e63f0b6c6d07c6b55a17fa8f20e78bf5dd1"
        },
        {
            "url": "https://fcc.report//FCC-ID/K7SF9K1105V2/3060701.pdf",
            "name": "3060701.pdf",
            "type": "Cover Letter(s)",
            "description": "Class II Permissive Change Letter",
            "date": "2016-07-13",
            "sha256": "9f633c24ac8f5d0a0813cff1fb5662cb53f44245ab6c239a2b17b9b15e99303a"
        }
    ]
}