{
    "additional_chips": [],
    "brand": "Swisscom",
    "commercial": {
        "amazon_asin": [],
        "availability": "",
        "deal_extreme": "",
        "ean": [],
        "end_of_life_date": "",
        "newegg": [],
        "release_date": "2016-06-01",
        "upc": []
    },
    "cpus": [
        {
            "chip_type": "ARM",
            "chip_type_revision": "Cortex-A53 (v7)",
            "description": "",
            "extra_info": "",
            "manufacturer": "Marvell",
            "manufacturer_verified": true,
            "model": "88DE3218",
            "model_verified": false
        }
    ],
    "defaults": {
        "ip": "",
        "ip_comment": "",
        "logins": [],
        "logins_comment": "",
        "password": "",
        "password_comment": "",
        "ssid_regexes": [],
        "ssids": [],
        "uses_dhcp": ""
    },
    "device_types": [
        "Android media player"
    ],
    "expansions": [
        "M.2 (NGFF)",
        "USB 2.0"
    ],
    "flags": [
        "Audio out",
        "HDMI"
    ],
    "flash": [
        {
            "chip_type": "",
            "chip_type_revision": "",
            "description": "",
            "extra_info": "",
            "manufacturer": "SanDisk",
            "manufacturer_verified": true,
            "model": "SDINBDG4-16G",
            "model_verified": false
        }
    ],
    "has_jtag": "unknown",
    "has_serial_port": "yes",
    "images": [],
    "jtag": {
        "baud_rate": 0,
        "connector": "",
        "number_of_pins": 8,
        "populated": "unknown",
        "voltage": null
    },
    "manufacturer": {
        "country": "China",
        "model": "IP1400",
        "name": "Arcadyan",
        "revision": ""
    },
    "model": {
        "model": "TV Box",
        "part_number": "IP1400",
        "pcb_id": "141271320000J",
        "revision": "",
        "serial_number": "",
        "series": "",
        "submodel": "UHD",
        "subrevision": ""
    },
    "network": {
        "chips": [],
        "docsis_version": "",
        "ethernet_oui": [
            {
                "name": "",
                "name_short": "",
                "oui": "0C:8E:29"
            }
        ],
        "jumbo_frames": "unknown",
        "lan_ports": 1,
        "mdix": "unknown",
        "wireless_oui": [
            {
                "name": "",
                "name_short": "",
                "oui": "0C:8E:29"
            }
        ]
    },
    "origins": [
        {
            "data_url": "Swisscom_TV_Box_UHD",
            "origin": "TechInfoDepot"
        }
    ],
    "power": {
        "barrel_length": 0.0,
        "connector": "",
        "inner_barrel_size": 0.0,
        "outer_barrel_size": 0.0,
        "polarity": "",
        "voltage": null,
        "voltage_type": ""
    },
    "power_supply": {
        "brand": "",
        "country": "",
        "e_level": "",
        "input_amperage": "",
        "input_connector": "",
        "input_current": "",
        "input_hz": "",
        "input_voltage": "",
        "model": "",
        "output_amperage": "",
        "output_connector": "",
        "output_current": "",
        "output_voltage": "",
        "revision": "",
        "style": ""
    },
    "radios": [
        {
            "capabilities": [],
            "chips": [
                {
                    "chip_type": "",
                    "chip_type_revision": "",
                    "description": "",
                    "extra_info": "",
                    "manufacturer": "Marvell",
                    "manufacturer_verified": true,
                    "model": "88W8897",
                    "model_verified": false
                }
            ],
            "interface": "M.2 (NGFF)",
            "module": "AzureWave AW-CM389NF",
            "oui": [],
            "standard": ""
        }
    ],
    "ram": [
        {
            "chip_type": "",
            "chip_type_revision": "",
            "description": "",
            "extra_info": "",
            "manufacturer": "Micron",
            "manufacturer_verified": false,
            "model": "MT41K256M16TW-107",
            "model_verified": false
        }
    ],
    "regulatory": {
        "fcc_ids": [
            {
                "fcc_date": "2014-07-09",
                "fcc_id": "TLZ-CM389NF",
                "fcc_type": "unknown",
                "grantee": "AzureWave Technologies, Inc."
            }
        ],
        "industry_canada_ids": [
            "6100A-CM389NF"
        ],
        "us_ids": [],
        "wifi_certified": "",
        "wifi_certified_date": ""
    },
    "serial": {
        "baud_rate": 0,
        "connector": "",
        "device": "",
        "number_of_pins": 4,
        "populated": "unknown",
        "voltage": null
    },
    "software": {
        "bootloader": {
            "extra_info": [],
            "manufacturer": "",
            "vendor_modified": "unknown",
            "version": ""
        },
        "ddwrt": "unknown",
        "files": [],
        "gargoyle": "unknown",
        "openwrt": "unknown",
        "os": "Android TV",
        "os_version": "",
        "packages": [],
        "programs": [],
        "sdk": "",
        "third_party": [],
        "tomato": "unknown"
    },
    "switch": [],
    "taglines": [
        "Swisscom TV Box (IP1400)"
    ],
    "title": "Swisscom TV Box UHD",
    "web": {
        "download_page": "",
        "product_page": [],
        "support_page": [
            "https://www.swisscom.ch/en/residential/help/device/blue-tv/tv-box-uhd.html"
        ],
        "techinfodepot": "",
        "wikidevi": "",
        "wikipedia": ""
    }
}